focus/__init__.py
focus/core.py
focus/focus.py
focus/utils.py
focus/version.py
focus/tests/__init__.py
focus/tests/test_focus.py
focus/tests/test_utils.py
focus_cfe-0.0.dev1.dist-info/LICENSE
focus_cfe-0.0.dev1.dist-info/METADATA
focus_cfe-0.0.dev1.dist-info/WHEEL
focus_cfe-0.0.dev1.dist-info/top_level.txt
focus_cfe-0.0.dev1.dist-info/RECORD
