Metadata-Version: 2.1
Name: focus-cfe
Version: 0.0.dev1
Summary: FOCUS is a python package for generating counterfactual explanations for a tree-based model
Home-page: UNKNOWN
Author: Kyosuke Morita
Author-email: kq441morita@gmail.com
License: UNKNOWN
Keywords: python,counterfactual explanation,binary classification,machine learning
Platform: UNKNOWN
Classifier: Development Status :: 3 - Alpha
Classifier: Intended Audience :: Education
Classifier: Intended Audience :: Science/Research
Classifier: Intended Audience :: Developers
Classifier: Intended Audience :: Information Technology
Classifier: License :: OSI Approved :: BSD License
Classifier: Programming Language :: Python :: 3
Classifier: Operating System :: MacOS :: MacOS X
Classifier: Operating System :: Microsoft :: Windows
